{"docker":[{"name":"FROM","lineno":1,"args":"alpine:3.9","raw":"FROM alpine:3.9"},{"name":"RUN","lineno":3,"args":"apk add --no-cache lua5.3 lua-filesystem lua-lyaml lua-http","raw":"RUN apk add --no-cache lua5.3 lua-filesystem lua-lyaml lua-http"},{"name":"COPY","lineno":5,"args":["fetch-latest-releases.lua","/usr/local/bin"],"raw":"COPY fetch-latest-releases.lua /usr/local/bin"},{"name":"VOLUME","lineno":7,"args":["/out"],"raw":"VOLUME /out"},{"name":"ENTRYPOINT","lineno":9,"args":["/usr/local/bin/fetch-latest-releases.lua"],"raw":"ENTRYPOINT [ \"/usr/local/bin/fetch-latest-releases.lua\" ]"}]}